{"v":"5.6.8","fr":60,"ip":0,"op":120,"w":500,"h":500,"nm":"30-Dalmatian","ddd":0,"assets":[{"id":"comp_0","layers":[{"ddd":0,"ind":1,"ty":3,"nm":"Main Stroke width - Color Ctrl","sr":1,"ks":{"o":{"a":0,"k":0,"ix":11},"r":{"a":0,"k":0,"ix":10},"p":{"a":0,"k":[250,250,0],"ix":2},"a":{"a":0,"k":[50,50,0],"ix":1},"s":{"a":0,"k":[100,100,100],"ix":6}},"ao":0,"ef":[{"ty":5,"nm":"Stroke width","np":3,"mn":"ADBE Slider Control","ix":1,"en":1,"ef":[{"ty":0,"nm":"Slider","mn":"ADBE Slider Control-0001","ix":1,"v":{"a":0,"k":16,"ix":1}}]},{"ty":5,"nm":"Base Color","np":3,"mn":"ADBE Color Control","ix":2,"en":1,"ef":[{"ty":2,"nm":"Color","mn":"ADBE Color Control-0001","ix":1,"v":{"a":0,"k":[0,0,0,1],"ix":1}}]},{"ty":5,"nm":"Highlight","np":3,"mn":"ADBE Color Control","ix":3,"en":1,"ef":[{"ty":2,"nm":"Color","mn":"ADBE Color Control-0001","ix":1,"v":{"a":0,"k":[1,0.698039233685,0.298039227724,1],"ix":1}}]}],"ip":0,"op":120,"st":0,"bm":0},{"ddd":0,"ind":2,"ty":4,"nm":"Dalmatian 2","parent":1,"td":1,"sr":1,"ks":{"o":{"a":0,"k":100,"ix":11},"r":{"a":1,"k":[{"i":{"x":[0.793],"y":[1]},"o":{"x":[0.207],"y":[0]},"t":0,"s":[0]},{"i":{"x":[0.793],"y":[1]},"o":{"x":[0.207],"y":[0]},"t":20.217,"s":[-18.105]},{"i":{"x":[0.793],"y":[1]},"o":{"x":[0.207],"y":[0]},"t":44.107,"s":[15.856]},{"i":{"x":[0.793],"y":[1]},"o":{"x":[0.207],"y":[0]},"t":64.324,"s":[-8]},{"i":{"x":[0.793],"y":[1]},"o":{"x":[0.207],"y":[0]},"t":85.459,"s":[4]},{"t":102,"s":[0]}],"ix":10},"p":{"a":1,"k":[{"i":{"x":0.7,"y":1},"o":{"x":0.3,"y":0},"t":0,"s":[57.75,58.25,0],"to":[0,7,0],"ti":[0,4.667,0]},{"i":{"x":0.7,"y":1},"o":{"x":0.3,"y":0},"t":18,"s":[57.75,100.25,0],"to":[0,-4.667,0],"ti":[0,0,0]},{"i":{"x":0.7,"y":1},"o":{"x":0.3,"y":0},"t":36,"s":[57.75,30.25,0],"to":[0,0,0],"ti":[0,-2,0]},{"i":{"x":0.7,"y":1},"o":{"x":0.3,"y":0},"t":53,"s":[57.75,100.25,0],"to":[0,2,0],"ti":[0,9.667,0]},{"i":{"x":0.7,"y":1},"o":{"x":0.3,"y":0},"t":71,"s":[57.75,42.25,0],"to":[0,-9.667,0],"ti":[0,-1.333,0]},{"i":{"x":0.7,"y":1},"o":{"x":0.3,"y":0},"t":90,"s":[57.75,70.25,0],"to":[0,1.333,0],"ti":[0,2,0]},{"t":105,"s":[57.75,58.25,0]}],"ix":2},"a":{"a":0,"k":[0,0,0],"ix":1},"s":{"a":0,"k":[100,100,100],"ix":6}},"ao":0,"shapes":[{"ty":"gr","it":[{"ty":"rc","d":1,"s":{"a":0,"k":[179,141],"ix":2},"p":{"a":0,"k":[0,0],"ix":3},"r":{"a":0,"k":0,"ix":4},"nm":"Rectangle Path 1","mn":"ADBE Vector Shape - Rect","hd":false},{"ty":"st","c":{"a":0,"k":[0,0,0,1],"ix":3},"o":{"a":0,"k":100,"ix":4},"w":{"a":0,"k":16,"ix":5},"lc":1,"lj":1,"ml":4,"bm":0,"nm":"Stroke 1","mn":"ADBE Vector Graphic - Stroke","hd":false},{"ty":"fl","c":{"a":0,"k":[1,0,0,1],"ix":4},"o":{"a":0,"k":100,"ix":5},"r":1,"bm":0,"nm":"Fill 1","mn":"ADBE Vector Graphic - Fill","hd":false},{"ty":"tr","p":{"a":0,"k":[-8.25,-35.75],"ix":2},"a":{"a":0,"k":[0,0],"ix":1},"s":{"a":0,"k":[100,100],"ix":3},"r":{"a":0,"k":0,"ix":6},"o":{"a":0,"k":100,"ix":7},"sk":{"a":0,"k":0,"ix":4},"sa":{"a":0,"k":0,"ix":5},"nm":"Transform"}],"nm":"Rectangle 1","np":3,"cix":2,"bm":0,"ix":1,"mn":"ADBE Vector Group","hd":false},{"ty":"gr","it":[{"ind":0,"ty":"sh","ix":1,"ks":{"a":1,"k":[{"i":{"x":0.64,"y":1},"o":{"x":0.36,"y":0},"t":0,"s":[{"i":[[0,0],[-33.431,4.693]],"o":[[0,0],[0,0]],"v":[[-75.772,20.071],[-25.699,31.13]],"c":false}]},{"i":{"x":0.64,"y":1},"o":{"x":0.36,"y":0},"t":16.604,"s":[{"i":[[0,0],[-33.431,4.693]],"o":[[0,0],[0,0]],"v":[[-75.772,20.071],[-25.699,31.13]],"c":false}]},{"i":{"x":0.64,"y":1},"o":{"x":0.36,"y":0},"t":35,"s":[{"i":[[0,0],[-33.431,4.693]],"o":[[0,0],[0,0]],"v":[[-75.772,20.071],[-25.699,31.13]],"c":false}]},{"t":55.603515625,"s":[{"i":[[0,0],[-33.431,4.693]],"o":[[0,0],[0,0]],"v":[[-75.772,20.071],[-25.699,31.13]],"c":false}]}],"ix":2},"nm":"Path 1","mn":"ADBE Vector Shape - Group","hd":false},{"ty":"st","c":{"a":0,"k":[0,0,0,1],"ix":3},"o":{"a":0,"k":100,"ix":4},"w":{"a":0,"k":16,"ix":5,"x":"var $bm_rt;\n$bm_rt = thisComp.layer('Main Stroke width - Color Ctrl').effect('Stroke width')('Slider');"},"lc":2,"lj":2,"bm":0,"nm":"Stroke 1","mn":"ADBE Vector Graphic - Stroke","hd":false},{"ty":"tr","p":{"a":0,"k":[0,0],"ix":2},"a":{"a":0,"k":[0,0],"ix":1},"s":{"a":0,"k":[100,100],"ix":3},"r":{"a":0,"k":0,"ix":6},"o":{"a":0,"k":100,"ix":7},"sk":{"a":0,"k":0,"ix":4},"sa":{"a":0,"k":0,"ix":5},"nm":"Transform"}],"nm":"Group 1","np":2,"cix":2,"bm":0,"ix":2,"mn":"ADBE Vector Group","hd":false},{"ty":"gr","it":[{"ind":0,"ty":"sh","ix":1,"ks":{"a":1,"k":[{"i":{"x":0.64,"y":1},"o":{"x":0.36,"y":0},"t":0,"s":[{"i":[[0,0],[0,0],[0,-21.365],[0,0],[13.918,0],[0,0],[10.838,34.279],[-9.811,7.636],[0,0],[0,0],[-23.138,0],[-14.508,-12.565],[0,0],[0,0],[3.748,-11.854],[28.753,0],[0,0],[0,13.918],[0,0],[11.17,18.212],[0,0]],"o":[[0,0],[-11.17,18.212],[0,0],[0,13.918],[0,0],[-28.753,0],[-3.748,-11.854],[0,0],[0,0],[14.548,-12.96],[22.731,0],[0,0],[0,0],[9.811,7.636],[-10.838,34.279],[0,0],[-13.918,0],[0,0],[0,-21.365],[0,0],[0,0]],"v":[[-61.139,-89.442],[-64.284,-84.314],[-81.365,-23.789],[-81.365,30.472],[-106.566,55.673],[-106.566,55.673],[-170.847,-44.952],[-160.744,-77.374],[-97.773,-126.384],[-58.521,-114.773],[-0.002,-135.85],[57.744,-115.452],[96.313,-126.384],[159.285,-77.374],[169.388,-44.952],[105.106,55.673],[105.106,55.673],[79.906,30.472],[79.906,-23.789],[62.824,-84.314],[59.679,-89.442]],"c":false}]},{"i":{"x":0.64,"y":1},"o":{"x":0.36,"y":0},"t":17,"s":[{"i":[[0,0],[0,0],[0,-21.365],[0.019,-0.02],[13.741,-2.191],[0,0],[16.098,32.137],[-8.484,9.084],[-0.023,-0.012],[0,0],[-23.138,0],[-14.508,-12.565],[-0.024,0.002],[0,0],[5.852,-10.966],[28.262,5.259],[0,0],[2.199,6.548],[0,0],[11.17,18.212],[0,0]],"o":[[0,0],[-11.17,18.212],[0,0],[-0.019,13.921],[0,0],[-28.388,4.527],[-5.567,-11.114],[0,0],[0.023,0.012],[14.548,-12.96],[22.731,0],[0,0],[0.024,-0.002],[8.247,9.3],[-16.923,31.711],[0,0],[-13.68,-2.546],[-0.015,-0.01],[0,-21.365],[0,0],[0,0]],"v":[[-61.139,-89.442],[-64.284,-84.314],[-81.371,-23.789],[-81.791,-0.399],[-81.122,61.315],[-81.122,61.315],[-160.431,-27.909],[-155.561,-61.51],[-101.106,-119.812],[-58.521,-114.773],[-0.002,-135.85],[57.744,-115.452],[99.503,-118.279],[152.434,-58.588],[156.434,-24.872],[74.846,62.275],[74.846,62.275],[80.188,6.546],[79.906,-23.789],[62.824,-84.314],[59.679,-89.442]],"c":false}]},{"i":{"x":0.64,"y":1},"o":{"x":0.36,"y":0},"t":35,"s":[{"i":[[0,0],[0,0],[0,-21.365],[15.838,-16.766],[12.382,6.355],[0,0],[-6.009,35.446],[-12.216,2.314],[-19.141,-10.31],[0,0],[-23.138,0],[-14.508,-12.565],[-20.23,2.08],[0,0],[-1.398,-12.354],[26.267,-11.696],[0,0],[12.586,8.047],[0,0],[11.17,18.212],[0,0]],"o":[[0,0],[-11.17,18.212],[0,0],[-15.838,16.766],[0,0],[-25.581,-13.128],[2.078,-12.258],[0,0],[19.141,10.31],[14.548,-12.96],[22.731,0],[0,0],[20.23,-2.08],[12.069,2.985],[4.043,35.724],[0,0],[-12.714,5.661],[-12.586,-8.047],[0,-21.365],[0,0],[0,0]],"v":[[-61.139,-89.442],[-64.284,-84.314],[-85.865,-23.789],[-139.162,4.734],[-173.088,15.648],[-173.088,15.648],[-184.335,-103.225],[-160.543,-127.458],[-82.141,-142.31],[-58.521,-114.773],[-0.002,-135.85],[57.744,-115.452],[84.77,-141.92],[162.232,-122.763],[184.65,-97.254],[166.858,20.817],[166.858,20.817],[133.586,8.047],[79.906,-23.789],[62.824,-84.314],[59.679,-89.442]],"c":false}]},{"t":55.603515625,"s":[{"i":[[0,0],[0,0],[0,-21.365],[0,0],[13.918,0],[0,0],[10.838,34.279],[-9.811,7.636],[0,0],[0,0],[-23.138,0],[-14.508,-12.565],[0,0],[0,0],[3.748,-11.854],[28.753,0],[0,0],[0,13.918],[0,0],[11.17,18.212],[0,0]],"o":[[0,0],[-11.17,18.212],[0,0],[0,13.918],[0,0],[-28.753,0],[-3.748,-11.854],[0,0],[0,0],[14.548,-12.96],[22.731,0],[0,0],[0,0],[9.811,7.636],[-10.838,34.279],[0,0],[-13.918,0],[0,0],[0,-21.365],[0,0],[0,0]],"v":[[-61.139,-89.442],[-64.284,-84.314],[-81.365,-23.789],[-81.365,30.472],[-106.566,55.673],[-106.566,55.673],[-170.847,-44.952],[-160.744,-77.374],[-97.773,-126.384],[-58.521,-114.773],[-0.002,-135.85],[57.744,-115.452],[96.313,-126.384],[159.285,-77.374],[169.388,-44.952],[105.106,55.673],[105.106,55.673],[79.906,30.472],[79.906,-23.789],[62.824,-84.314],[59.679,-89.442]],"c":false}]}],"ix":2},"nm":"Path 1","mn":"ADBE Vector Shape - Group","hd":false},{"ty":"st","c":{"a":0,"k":[0,0,0,1],"ix":3},"o":{"a":0,"k":100,"ix":4},"w":{"a":0,"k":16,"ix":5,"x":"var $bm_rt;\n$bm_rt = thisComp.layer('Main Stroke width - Color Ctrl').effect('Stroke width')('Slider');"},"lc":2,"lj":2,"bm":0,"nm":"Stroke 1","mn":"ADBE Vector Graphic - Stroke","hd":false},{"ty":"tr","p":{"a":0,"k":[0,0],"ix":2},"a":{"a":0,"k":[0,0],"ix":1},"s":{"a":0,"k":[100,100],"ix":3},"r":{"a":0,"k":0,"ix":6},"o":{"a":0,"k":100,"ix":7},"sk":{"a":0,"k":0,"ix":4},"sa":{"a":0,"k":0,"ix":5},"nm":"Transform"}],"nm":"Group 2","np":2,"cix":2,"bm":0,"ix":3,"mn":"ADBE Vector Group","hd":false},{"ty":"gr","it":[{"ind":0,"ty":"sh","ix":1,"ks":{"a":1,"k":[{"i":{"x":0.64,"y":1},"o":{"x":0.36,"y":0},"t":0,"s":[{"i":[[0,0],[0,0],[16.717,0],[0,0],[3.257,13.204],[3.628,12.506],[0,0]],"o":[[0,0],[0,16.717],[0,0],[-14.21,0],[-3.119,-12.643],[0,0],[0,0]],"v":[[-0.73,65.615],[-0.73,73.508],[-29.998,103.778],[-29.998,103.778],[-59.388,80.783],[-69.131,42.961],[-81.365,0.792]],"c":false}]},{"i":{"x":0.64,"y":1},"o":{"x":0.36,"y":0},"t":16.604,"s":[{"i":[[0,0],[0,0],[16.717,0],[0,0],[3.257,13.204],[3.628,12.506],[0,0]],"o":[[0,0],[0,16.717],[0,0],[-14.21,0],[-3.119,-12.643],[0,0],[0,0]],"v":[[-0.73,65.615],[-0.73,73.508],[-29.998,103.778],[-29.998,103.778],[-59.388,80.783],[-69.131,42.961],[-81.365,0.792]],"c":false}]},{"i":{"x":0.64,"y":1},"o":{"x":0.36,"y":0},"t":35,"s":[{"i":[[0,0],[0,0],[16.717,0],[0,0],[3.257,13.204],[3.628,12.506],[0,0]],"o":[[0,0],[0,16.717],[0,0],[-14.21,0],[-3.119,-12.643],[0,0],[0,0]],"v":[[-0.73,65.615],[-0.73,73.508],[-29.998,103.778],[-29.998,103.778],[-59.388,80.783],[-69.131,42.961],[-86.365,-20.208]],"c":false}]},{"t":55.603515625,"s":[{"i":[[0,0],[0,0],[16.717,0],[0,0],[3.257,13.204],[3.628,12.506],[0,0]],"o":[[0,0],[0,16.717],[0,0],[-14.21,0],[-3.119,-12.643],[0,0],[0,0]],"v":[[-0.73,65.615],[-0.73,73.508],[-29.998,103.778],[-29.998,103.778],[-59.388,80.783],[-69.131,42.961],[-81.365,0.792]],"c":false}]}],"ix":2},"nm":"Path 1","mn":"ADBE Vector Shape - Group","hd":false},{"ty":"st","c":{"a":0,"k":[0,0,0,1],"ix":3},"o":{"a":0,"k":100,"ix":4},"w":{"a":0,"k":16,"ix":5,"x":"var $bm_rt;\n$bm_rt = thisComp.layer('Main Stroke width - Color Ctrl').effect('Stroke width')('Slider');"},"lc":2,"lj":2,"bm":0,"nm":"Stroke 1","mn":"ADBE Vector Graphic - Stroke","hd":false},{"ty":"tr","p":{"a":0,"k":[0,0],"ix":2},"a":{"a":0,"k":[0,0],"ix":1},"s":{"a":0,"k":[100,100],"ix":3},"r":{"a":0,"k":0,"ix":6},"o":{"a":0,"k":100,"ix":7},"sk":{"a":0,"k":0,"ix":4},"sa":{"a":0,"k":0,"ix":5},"nm":"Transform"}],"nm":"Group 4","np":2,"cix":2,"bm":0,"ix":4,"mn":"ADBE Vector Group","hd":false},{"ty":"gr","it":[{"ind":0,"ty":"sh","ix":1,"ks":{"a":1,"k":[{"i":{"x":0.64,"y":1},"o":{"x":0.36,"y":0},"t":0,"s":[{"i":[[0,0],[0,0],[2.971,-14.517],[14.628,0],[0,0],[0,16.717],[0,0]],"o":[[0,0],[-3.921,14.289],[-2.823,13.793],[0,0],[-16.718,0],[0,0],[0,0]],"v":[[79.906,5.896],[71.512,36.488],[60.739,79.609],[31.084,103.778],[31.084,103.778],[-0.73,73.508],[-0.73,66.452]],"c":false}]},{"i":{"x":0.64,"y":1},"o":{"x":0.36,"y":0},"t":16.604,"s":[{"i":[[0,0],[0,0],[2.971,-14.517],[14.628,0],[0,0],[0,16.717],[0,0]],"o":[[0,0],[-3.921,14.289],[-2.823,13.793],[0,0],[-16.718,0],[0,0],[0,0]],"v":[[79.906,5.896],[71.512,36.488],[60.739,79.609],[31.084,103.778],[31.084,103.778],[-0.73,73.508],[-0.73,66.452]],"c":false}]},{"i":{"x":0.64,"y":1},"o":{"x":0.36,"y":0},"t":35,"s":[{"i":[[0,0],[0,0],[2.971,-14.517],[14.628,0],[0,0],[0,16.717],[0,0]],"o":[[0,0],[-3.921,14.289],[-2.823,13.793],[0,0],[-16.718,0],[0,0],[0,0]],"v":[[79.906,-22.104],[71.512,36.488],[60.739,79.609],[31.084,103.778],[31.084,103.778],[-0.73,73.508],[-0.73,66.452]],"c":false}]},{"t":55.603515625,"s":[{"i":[[0,0],[0,0],[2.971,-14.517],[14.628,0],[0,0],[0,16.717],[0,0]],"o":[[0,0],[-3.921,14.289],[-2.823,13.793],[0,0],[-16.718,0],[0,0],[0,0]],"v":[[79.906,5.896],[71.512,36.488],[60.739,79.609],[31.084,103.778],[31.084,103.778],[-0.73,73.508],[-0.73,66.452]],"c":false}]}],"ix":2},"nm":"Path 1","mn":"ADBE Vector Shape - Group","hd":false},{"ty":"st","c":{"a":0,"k":[0,0,0,1],"ix":3},"o":{"a":0,"k":100,"ix":4},"w":{"a":0,"k":16,"ix":5,"x":"var $bm_rt;\n$bm_rt = thisComp.layer('Main Stroke width - Color Ctrl').effect('Stroke width')('Slider');"},"lc":2,"lj":2,"bm":0,"nm":"Stroke 1","mn":"ADBE Vector Graphic - Stroke","hd":false},{"ty":"tr","p":{"a":0,"k":[0,0],"ix":2},"a":{"a":0,"k":[0,0],"ix":1},"s":{"a":0,"k":[100,100],"ix":3},"r":{"a":0,"k":0,"ix":6},"o":{"a":0,"k":100,"ix":7},"sk":{"a":0,"k":0,"ix":4},"sa":{"a":0,"k":0,"ix":5},"nm":"Transform"}],"nm":"Group 5","np":2,"cix":2,"bm":0,"ix":5,"mn":"ADBE Vector Group","hd":false},{"ty":"gr","it":[{"ind":0,"ty":"sh","ix":1,"ks":{"a":1,"k":[{"i":{"x":0.64,"y":1},"o":{"x":0.36,"y":0},"t":0,"s":[{"i":[[0,0],[0,0],[-5.74,6.314],[-6.68,0],[0,0],[-4.165,-4.582],[6.657,-5.338]],"o":[[0,0],[-6.657,-5.338],[4.165,-4.582],[0,0],[6.68,0],[5.74,6.314],[0,0]],"v":[[-0.73,65.615],[-21.336,49.09],[-23.208,27.53],[-6.354,20.071],[4.895,20.071],[21.749,27.53],[19.877,49.09]],"c":true}]},{"i":{"x":0.64,"y":1},"o":{"x":0.36,"y":0},"t":16.604,"s":[{"i":[[0,0],[0,0],[-5.74,6.314],[-6.68,0],[0,0],[-4.165,-4.582],[6.657,-5.338]],"o":[[0,0],[-6.657,-5.338],[4.165,-4.582],[0,0],[6.68,0],[5.74,6.314],[0,0]],"v":[[-0.73,65.615],[-21.336,49.09],[-23.208,27.53],[-6.354,20.071],[4.895,20.071],[21.749,27.53],[19.877,49.09]],"c":true}]},{"i":{"x":0.64,"y":1},"o":{"x":0.36,"y":0},"t":35,"s":[{"i":[[0,0],[0,0],[-5.74,6.314],[-6.68,0],[0,0],[-4.165,-4.582],[6.657,-5.338]],"o":[[0,0],[-6.657,-5.338],[4.165,-4.582],[0,0],[6.68,0],[5.74,6.314],[0,0]],"v":[[-0.73,65.615],[-21.336,49.09],[-23.208,27.53],[-6.354,20.071],[4.895,20.071],[21.749,27.53],[19.877,49.09]],"c":true}]},{"t":55.603515625,"s":[{"i":[[0,0],[0,0],[-5.74,6.314],[-6.68,0],[0,0],[-4.165,-4.582],[6.657,-5.338]],"o":[[0,0],[-6.657,-5.338],[4.165,-4.582],[0,0],[6.68,0],[5.74,6.314],[0,0]],"v":[[-0.73,65.615],[-21.336,49.09],[-23.208,27.53],[-6.354,20.071],[4.895,20.071],[21.749,27.53],[19.877,49.09]],"c":true}]}],"ix":2},"nm":"Path 1","mn":"ADBE Vector Shape - Group","hd":false},{"ty":"st","c":{"a":0,"k":[0,0,0,1],"ix":3},"o":{"a":0,"k":100,"ix":4},"w":{"a":0,"k":16,"ix":5,"x":"var $bm_rt;\n$bm_rt = thisComp.layer('Main Stroke width - Color Ctrl').effect('Stroke width')('Slider');"},"lc":2,"lj":2,"bm":0,"nm":"Stroke 1","mn":"ADBE Vector Graphic - Stroke","hd":false},{"ty":"tr","p":{"a":0,"k":[0,0],"ix":2},"a":{"a":0,"k":[0,0],"ix":1},"s":{"a":0,"k":[100,100],"ix":3},"r":{"a":0,"k":0,"ix":6},"o":{"a":0,"k":100,"ix":7},"sk":{"a":0,"k":0,"ix":4},"sa":{"a":0,"k":0,"ix":5},"nm":"Transform"}],"nm":"Group 6","np":2,"cix":2,"bm":0,"ix":6,"mn":"ADBE Vector Group","hd":false},{"ty":"gr","it":[{"ty":"gr","it":[{"ind":0,"ty":"sh","ix":1,"ks":{"a":1,"k":[{"i":{"x":0.64,"y":1},"o":{"x":0.36,"y":0},"t":0,"s":[{"i":[[0,0],[0,0]],"o":[[0,0],[0,0]],"v":[[38.268,-31.947],[38.268,-10.548]],"c":false}]},{"i":{"x":0.64,"y":1},"o":{"x":0.36,"y":0},"t":16.604,"s":[{"i":[[0,0],[0,0]],"o":[[0,0],[0,0]],"v":[[38.268,-31.947],[38.268,-10.548]],"c":false}]},{"i":{"x":0.64,"y":1},"o":{"x":0.36,"y":0},"t":35,"s":[{"i":[[0,0],[0,0]],"o":[[0,0],[0,0]],"v":[[38.268,-31.947],[38.268,-10.548]],"c":false}]},{"t":55.603515625,"s":[{"i":[[0,0],[0,0]],"o":[[0,0],[0,0]],"v":[[38.268,-31.947],[38.268,-10.548]],"c":false}]}],"ix":2},"nm":"Path 1","mn":"ADBE Vector Shape - Group","hd":false},{"ty":"st","c":{"a":0,"k":[0,0,0,1],"ix":3},"o":{"a":0,"k":100,"ix":4},"w":{"a":0,"k":16,"ix":5,"x":"var $bm_rt;\n$bm_rt = thisComp.layer('Main Stroke width - Color Ctrl').effect('Stroke width')('Slider');"},"lc":2,"lj":2,"bm":0,"nm":"Stroke 1","mn":"ADBE Vector Graphic - Stroke","hd":false},{"ty":"tr","p":{"a":0,"k":[0,0],"ix":2},"a":{"a":0,"k":[0,0],"ix":1},"s":{"a":0,"k":[100,100],"ix":3},"r":{"a":0,"k":0,"ix":6},"o":{"a":0,"k":100,"ix":7},"sk":{"a":0,"k":0,"ix":4},"sa":{"a":0,"k":0,"ix":5},"nm":"Transform"}],"nm":"Group 1","np":2,"cix":2,"bm":0,"ix":1,"mn":"ADBE Vector Group","hd":false},{"ty":"gr","it":[{"ind":0,"ty":"sh","ix":1,"ks":{"a":1,"k":[{"i":{"x":0.64,"y":1},"o":{"x":0.36,"y":0},"t":0,"s":[{"i":[[0,0],[0,0]],"o":[[0,0],[0,0]],"v":[[-38.273,-31.947],[-38.273,-10.548]],"c":false}]},{"i":{"x":0.64,"y":1},"o":{"x":0.36,"y":0},"t":16.604,"s":[{"i":[[0,0],[0,0]],"o":[[0,0],[0,0]],"v":[[-38.273,-31.947],[-38.273,-10.548]],"c":false}]},{"i":{"x":0.64,"y":1},"o":{"x":0.36,"y":0},"t":35,"s":[{"i":[[0,0],[0,0]],"o":[[0,0],[0,0]],"v":[[-38.273,-31.947],[-38.273,-10.548]],"c":false}]},{"t":55.603515625,"s":[{"i":[[0,0],[0,0]],"o":[[0,0],[0,0]],"v":[[-38.273,-31.947],[-38.273,-10.548]],"c":false}]}],"ix":2},"nm":"Path 1","mn":"ADBE Vector Shape - Group","hd":false},{"ty":"st","c":{"a":0,"k":[0,0,0,1],"ix":3},"o":{"a":0,"k":100,"ix":4},"w":{"a":0,"k":16,"ix":5,"x":"var $bm_rt;\n$bm_rt = thisComp.layer('Main Stroke width - Color Ctrl').effect('Stroke width')('Slider');"},"lc":2,"lj":2,"bm":0,"nm":"Stroke 1","mn":"ADBE Vector Graphic - Stroke","hd":false},{"ty":"tr","p":{"a":0,"k":[0,0],"ix":2},"a":{"a":0,"k":[0,0],"ix":1},"s":{"a":0,"k":[100,100],"ix":3},"r":{"a":0,"k":0,"ix":6},"o":{"a":0,"k":100,"ix":7},"sk":{"a":0,"k":0,"ix":4},"sa":{"a":0,"k":0,"ix":5},"nm":"Transform"}],"nm":"Group 2","np":2,"cix":2,"bm":0,"ix":2,"mn":"ADBE Vector Group","hd":false},{"ty":"tr","p":{"a":0,"k":[0,0],"ix":2},"a":{"a":0,"k":[0,0],"ix":1},"s":{"a":0,"k":[100,100],"ix":3},"r":{"a":0,"k":0,"ix":6},"o":{"a":0,"k":100,"ix":7},"sk":{"a":0,"k":0,"ix":4},"sa":{"a":0,"k":0,"ix":5},"nm":"Transform"}],"nm":"Group 7","np":2,"cix":2,"bm":0,"ix":7,"mn":"ADBE Vector Group","hd":false},{"ty":"gr","it":[{"ind":0,"ty":"sh","ix":1,"ks":{"a":1,"k":[{"i":{"x":0.64,"y":1},"o":{"x":0.36,"y":0},"t":0,"s":[{"i":[[0,0],[0.493,-21.387],[7.632,-6.693]],"o":[[22.158,-5.185],[-0.234,10.152],[0,0]],"v":[[-159.449,-31.909],[-118.625,4.377],[-131.478,32.004]],"c":false}]},{"i":{"x":0.64,"y":1},"o":{"x":0.36,"y":0},"t":16.604,"s":[{"i":[[0,0],[-2.896,-21.195],[6.477,-7.816]],"o":[[21.059,-8.624],[1.375,10.061],[0,0]],"v":[[-147.085,-16.743],[-101.035,12.627],[-109.356,41.94]],"c":false}]},{"i":{"x":0.64,"y":1},"o":{"x":0.36,"y":0},"t":35,"s":[{"i":[[0,0],[10.204,-18.802],[9.846,-2.47]],"o":[[22.081,5.504],[-4.843,8.925],[0,0]],"v":[[-180.15,-86.417],[-160.396,-35.495],[-184.445,-16.785]],"c":false}]},{"t":55.603515625,"s":[{"i":[[0,0],[0.493,-21.387],[7.632,-6.693]],"o":[[22.158,-5.185],[-0.234,10.152],[0,0]],"v":[[-159.449,-31.909],[-118.625,4.377],[-131.478,32.004]],"c":false}]}],"ix":2},"nm":"Path 1","mn":"ADBE Vector Shape - Group","hd":false},{"ty":"st","c":{"a":0,"k":[0.20000000298,0.800000011921,0.800000011921,1],"ix":3},"o":{"a":0,"k":100,"ix":4},"w":{"a":0,"k":16,"ix":5,"x":"var $bm_rt;\n$bm_rt = thisComp.layer('Main Stroke width - Color Ctrl').effect('Stroke width')('Slider');"},"lc":2,"lj":2,"bm":0,"nm":"Stroke 1","mn":"ADBE Vector Graphic - Stroke","hd":false},{"ty":"tr","p":{"a":0,"k":[0,0],"ix":2},"a":{"a":0,"k":[0,0],"ix":1},"s":{"a":0,"k":[100,100],"ix":3},"r":{"a":0,"k":0,"ix":6},"o":{"a":0,"k":100,"ix":7},"sk":{"a":0,"k":0,"ix":4},"sa":{"a":0,"k":0,"ix":5},"nm":"Transform"}],"nm":"Group 8","np":2,"cix":2,"bm":0,"ix":8,"mn":"ADBE Vector Group","hd":false},{"ty":"gr","it":[{"ind":0,"ty":"sh","ix":1,"ks":{"a":1,"k":[{"i":{"x":0.64,"y":1},"o":{"x":0.36,"y":0},"t":0,"s":[{"i":[[0,0],[-0.157,-10.538],[0,0],[-21.919,3.823]],"o":[[-7.661,7.238],[0,0],[0.355,23.805],[0,0]],"v":[[131.603,-92.199],[118.947,-62.218],[118.947,-62.218],[162.891,-25.68]],"c":false}]},{"i":{"x":0.64,"y":1},"o":{"x":0.36,"y":0},"t":16.604,"s":[{"i":[[0,0],[1.78,-10.388],[0,0],[-22.248,-0.266]],"o":[[-8.86,5.708],[0,0],[-4.022,23.466],[0,0]],"v":[[127.933,-78.168],[109.987,-51.02],[109.987,-51.02],[146.476,-7.035]],"c":false}]},{"i":{"x":0.64,"y":1},"o":{"x":0.36,"y":0},"t":35,"s":[{"i":[[0,0],[-4.43,-9.563],[0,0],[-18.468,12.409]],"o":[[-4.055,9.728],[0,0],[10.008,21.602],[0,0]],"v":[[130.913,-125.046],[131.547,-92.509],[131.547,-92.509],[186.554,-77.007]],"c":false}]},{"t":55.603515625,"s":[{"i":[[0,0],[-0.157,-10.538],[0,0],[-21.919,3.823]],"o":[[-7.661,7.238],[0,0],[0.355,23.805],[0,0]],"v":[[131.603,-92.199],[118.947,-62.218],[118.947,-62.218],[162.891,-25.68]],"c":false}]}],"ix":2},"nm":"Path 1","mn":"ADBE Vector Shape - Group","hd":false},{"ty":"st","c":{"a":0,"k":[0.20000000298,0.800000011921,0.800000011921,1],"ix":3},"o":{"a":0,"k":100,"ix":4},"w":{"a":0,"k":16,"ix":5,"x":"var $bm_rt;\n$bm_rt = thisComp.layer('Main Stroke width - Color Ctrl').effect('Stroke width')('Slider');"},"lc":2,"lj":2,"bm":0,"nm":"Stroke 1","mn":"ADBE Vector Graphic - Stroke","hd":false},{"ty":"tr","p":{"a":0,"k":[0,0],"ix":2},"a":{"a":0,"k":[0,0],"ix":1},"s":{"a":0,"k":[100,100],"ix":3},"r":{"a":0,"k":0,"ix":6},"o":{"a":0,"k":100,"ix":7},"sk":{"a":0,"k":0,"ix":4},"sa":{"a":0,"k":0,"ix":5},"nm":"Transform"}],"nm":"Group 9","np":2,"cix":2,"bm":0,"ix":9,"mn":"ADBE Vector Group","hd":false},{"ty":"gr","it":[{"ind":0,"ty":"sh","ix":1,"ks":{"a":1,"k":[{"i":{"x":0.64,"y":1},"o":{"x":0.36,"y":0},"t":0,"s":[{"i":[[0,0],[-28.023,-9.423],[0,0],[0,0]],"o":[[0,0],[19.343,6.505],[0,0],[0,0]],"v":[[-78.606,-48.899],[-26.566,-62.09],[0.272,-31.947],[-0.359,20.071]],"c":false}]},{"i":{"x":0.64,"y":1},"o":{"x":0.36,"y":0},"t":16.604,"s":[{"i":[[0,0],[-28.023,-9.423],[0,0],[0,0]],"o":[[0,0],[19.343,6.505],[0,0],[0,0]],"v":[[-78.606,-48.899],[-26.566,-62.09],[0.272,-31.947],[-0.359,20.071]],"c":false}]},{"i":{"x":0.64,"y":1},"o":{"x":0.36,"y":0},"t":35,"s":[{"i":[[0,0],[-28.023,-9.423],[0,0],[0,0]],"o":[[0,0],[19.343,6.505],[0,0],[0,0]],"v":[[-78.606,-48.899],[-26.566,-62.09],[0.272,-31.947],[-0.359,20.071]],"c":false}]},{"t":55.603515625,"s":[{"i":[[0,0],[-28.023,-9.423],[0,0],[0,0]],"o":[[0,0],[19.343,6.505],[0,0],[0,0]],"v":[[-78.606,-48.899],[-26.566,-62.09],[0.272,-31.947],[-0.359,20.071]],"c":false}]}],"ix":2},"nm":"Path 1","mn":"ADBE Vector Shape - Group","hd":false},{"ty":"st","c":{"a":0,"k":[0.20000000298,0.800000011921,0.800000011921,1],"ix":3},"o":{"a":0,"k":100,"ix":4},"w":{"a":0,"k":16,"ix":5,"x":"var $bm_rt;\n$bm_rt = thisComp.layer('Main Stroke width - Color Ctrl').effect('Stroke width')('Slider');"},"lc":2,"lj":2,"bm":0,"nm":"Stroke 1","mn":"ADBE Vector Graphic - Stroke","hd":false},{"ty":"tr","p":{"a":0,"k":[0,0],"ix":2},"a":{"a":0,"k":[0,0],"ix":1},"s":{"a":0,"k":[100,100],"ix":3},"r":{"a":0,"k":0,"ix":6},"o":{"a":0,"k":100,"ix":7},"sk":{"a":0,"k":0,"ix":4},"sa":{"a":0,"k":0,"ix":5},"nm":"Transform"}],"nm":"Group 10","np":2,"cix":2,"bm":0,"ix":10,"mn":"ADBE Vector Group","hd":false},{"ty":"fl","c":{"a":0,"k":[1,0,0,1],"ix":4},"o":{"a":0,"k":100,"ix":5},"r":1,"bm":0,"nm":"Fill 1","mn":"ADBE Vector Graphic - Fill","hd":false}],"ip":0,"op":120,"st":0,"bm":0},{"ddd":0,"ind":3,"ty":4,"nm":"Tongue","parent":5,"tt":2,"sr":1,"ks":{"o":{"a":0,"k":100,"ix":11},"r":{"a":0,"k":0,"ix":10},"p":{"a":1,"k":[{"i":{"x":0.72,"y":1},"o":{"x":0.28,"y":0},"t":0,"s":[-21,8.5,0],"to":[0.833,14.5,0],"ti":[-0.667,-9.167,0]},{"i":{"x":0.72,"y":1},"o":{"x":0.28,"y":0},"t":12,"s":[-16,95.5,0],"to":[0.667,9.167,0],"ti":[-0.167,1.083,0]},{"i":{"x":0.72,"y":1},"o":{"x":0.28,"y":0},"t":25,"s":[-17,63.5,0],"to":[0.167,-1.083,0],"ti":[0,0,0]},{"i":{"x":0.72,"y":1},"o":{"x":0.28,"y":0},"t":38,"s":[-15,89,0],"to":[0,0,0],"ti":[0,0,0]},{"i":{"x":0.72,"y":1},"o":{"x":0.28,"y":0},"t":52,"s":[-17,63.5,0],"to":[0,0,0],"ti":[0.667,9.167,0]},{"i":{"x":0.72,"y":1},"o":{"x":0.28,"y":0},"t":66,"s":[-15,89,0],"to":[-0.667,-9.167,0],"ti":[1,13.417,0]},{"t":80,"s":[-21,8.5,0]}],"ix":2},"a":{"a":0,"k":[-1612.729,106.5,0],"ix":1},"s":{"a":0,"k":[100,100,100],"ix":6}},"ao":0,"shapes":[{"ty":"gr","it":[{"ind":0,"ty":"sh","ix":1,"ks":{"a":0,"k":{"i":[[0,0],[0,0]],"o":[[0,0],[0,0]],"v":[[-1597.479,117.75],[-1597.479,137.75]],"c":false},"ix":2},"nm":"Path 1","mn":"ADBE Vector Shape - Group","hd":false},{"ty":"st","c":{"a":0,"k":[0.2,0.8,0.8,1],"ix":3,"x":"var $bm_rt;\n$bm_rt = thisComp.layer('Main Stroke width - Color Ctrl').effect('Highlight')('Color');"},"o":{"a":0,"k":100,"ix":4},"w":{"a":0,"k":16,"ix":5,"x":"var $bm_rt;\n$bm_rt = thisComp.layer('Main Stroke width - Color Ctrl').effect('Stroke width')('Slider');"},"lc":2,"lj":1,"ml":4,"bm":0,"nm":"Stroke 1","mn":"ADBE Vector Graphic - Stroke","hd":false},{"ty":"tr","p":{"a":0,"k":[0,0],"ix":2},"a":{"a":0,"k":[0,0],"ix":1},"s":{"a":0,"k":[100,100],"ix":3},"r":{"a":0,"k":0,"ix":6},"o":{"a":0,"k":100,"ix":7},"sk":{"a":0,"k":0,"ix":4},"sa":{"a":0,"k":0,"ix":5},"nm":"Transform"}],"nm":"Shape 1","np":2,"cix":2,"bm":0,"ix":1,"mn":"ADBE Vector Group","hd":false},{"ty":"gr","it":[{"ty":"rc","d":1,"s":{"a":0,"k":[446,421],"ix":2},"p":{"a":0,"k":[0,0],"ix":3},"r":{"a":0,"k":0,"ix":4},"nm":"Rectangle Path 1","mn":"ADBE Vector Shape - Rect","hd":false},{"ty":"st","c":{"a":0,"k":[0,0,0,1],"ix":3,"x":"var $bm_rt;\n$bm_rt = thisComp.layer('Main Stroke width - Color Ctrl').effect('Base Color')('Color');"},"o":{"a":0,"k":0,"ix":4},"w":{"a":0,"k":16,"ix":5,"x":"var $bm_rt;\n$bm_rt = thisComp.layer('Main Stroke width - Color Ctrl').effect('Stroke width')('Slider');"},"lc":1,"lj":1,"ml":4,"bm":0,"nm":"Stroke 1","mn":"ADBE Vector Graphic - Stroke","hd":false},{"ty":"tr","p":{"a":0,"k":[-1612.73,106.5],"ix":2},"a":{"a":0,"k":[0,0],"ix":1},"s":{"a":0,"k":[100,100],"ix":3},"r":{"a":0,"k":0,"ix":6},"o":{"a":0,"k":100,"ix":7},"sk":{"a":0,"k":0,"ix":4},"sa":{"a":0,"k":0,"ix":5},"nm":"Transform"}],"nm":"Rectangle 1","np":2,"cix":2,"bm":0,"ix":2,"mn":"ADBE Vector Group","hd":false},{"ty":"gr","it":[{"ind":0,"ty":"sh","ix":1,"ks":{"a":0,"k":{"i":[[0,0],[0,0],[-12.27,0],[0,0],[0,12.27],[0,0]],"o":[[0,0],[0,12.27],[0,0],[12.27,0],[0,0],[0,0]],"v":[[-1619.162,119.322],[-1619.196,144.68],[-1596.98,166.896],[-1596.98,166.896],[-1574.764,144.68],[-1574.729,113.96]],"c":false},"ix":2},"nm":"Path 1","mn":"ADBE Vector Shape - Group","hd":false},{"ty":"st","c":{"a":0,"k":[0.20000000298,0.800000011921,0.800000011921,1],"ix":3,"x":"var $bm_rt;\n$bm_rt = thisComp.layer('Main Stroke width - Color Ctrl').effect('Highlight')('Color');"},"o":{"a":0,"k":100,"ix":4},"w":{"a":0,"k":16,"ix":5,"x":"var $bm_rt;\n$bm_rt = thisComp.layer('Main Stroke width - Color Ctrl').effect('Stroke width')('Slider');"},"lc":2,"lj":2,"bm":0,"nm":"Stroke 1","mn":"ADBE Vector Graphic - Stroke","hd":false},{"ty":"tr","p":{"a":0,"k":[0,0],"ix":2},"a":{"a":0,"k":[0,0],"ix":1},"s":{"a":0,"k":[100,100],"ix":3},"r":{"a":0,"k":0,"ix":6},"o":{"a":0,"k":100,"ix":7},"sk":{"a":0,"k":0,"ix":4},"sa":{"a":0,"k":0,"ix":5},"nm":"Transform"}],"nm":"Group 1","np":2,"cix":2,"bm":0,"ix":3,"mn":"ADBE Vector Group","hd":false}],"ip":0,"op":120,"st":0,"bm":0},{"ddd":0,"ind":4,"ty":4,"nm":"Tongue 2","parent":5,"td":1,"sr":1,"ks":{"o":{"a":0,"k":100,"ix":11},"r":{"a":0,"k":0,"ix":10},"p":{"a":1,"k":[{"i":{"x":0.72,"y":1},"o":{"x":0.28,"y":0},"t":0,"s":[-21,8.5,0],"to":[0.833,14.5,0],"ti":[-0.667,-9.167,0]},{"i":{"x":0.72,"y":1},"o":{"x":0.28,"y":0},"t":12,"s":[-16,95.5,0],"to":[0.667,9.167,0],"ti":[-0.167,1.083,0]},{"i":{"x":0.72,"y":1},"o":{"x":0.28,"y":0},"t":25,"s":[-17,63.5,0],"to":[0.167,-1.083,0],"ti":[0,0,0]},{"i":{"x":0.72,"y":1},"o":{"x":0.28,"y":0},"t":38,"s":[-15,89,0],"to":[0,0,0],"ti":[0,0,0]},{"i":{"x":0.72,"y":1},"o":{"x":0.28,"y":0},"t":52,"s":[-17,63.5,0],"to":[0,0,0],"ti":[0.667,9.167,0]},{"i":{"x":0.72,"y":1},"o":{"x":0.28,"y":0},"t":66,"s":[-15,89,0],"to":[-0.667,-9.167,0],"ti":[1,13.417,0]},{"t":80,"s":[-21,8.5,0]}],"ix":2},"a":{"a":0,"k":[-1612.729,106.5,0],"ix":1},"s":{"a":0,"k":[100,100,100],"ix":6}},"ao":0,"shapes":[{"ty":"gr","it":[{"ind":0,"ty":"sh","ix":1,"ks":{"a":0,"k":{"i":[[0,0],[0,0],[-12.27,0],[0,0],[0,12.27],[0,0]],"o":[[0,0],[0,12.27],[0,0],[12.27,0],[0,0],[0,0]],"v":[[-1619.162,119.322],[-1619.196,144.68],[-1596.98,166.896],[-1596.98,166.896],[-1574.764,144.68],[-1574.729,113.96]],"c":false},"ix":2},"nm":"Path 1","mn":"ADBE Vector Shape - Group","hd":false},{"ty":"st","c":{"a":0,"k":[0.20000000298,0.800000011921,0.800000011921,1],"ix":3,"x":"var $bm_rt;\n$bm_rt = thisComp.layer('Main Stroke width - Color Ctrl').effect('Highlight')('Color');"},"o":{"a":0,"k":100,"ix":4},"w":{"a":0,"k":16,"ix":5,"x":"var $bm_rt;\n$bm_rt = thisComp.layer('Main Stroke width - Color Ctrl').effect('Stroke width')('Slider');"},"lc":2,"lj":2,"bm":0,"nm":"Stroke 1","mn":"ADBE Vector Graphic - Stroke","hd":false},{"ty":"tr","p":{"a":0,"k":[0,0],"ix":2},"a":{"a":0,"k":[0,0],"ix":1},"s":{"a":0,"k":[100,100],"ix":3},"r":{"a":0,"k":0,"ix":6},"o":{"a":0,"k":100,"ix":7},"sk":{"a":0,"k":0,"ix":4},"sa":{"a":0,"k":0,"ix":5},"nm":"Transform"}],"nm":"Group 1","np":2,"cix":2,"bm":0,"ix":1,"mn":"ADBE Vector Group","hd":false},{"ty":"fl","c":{"a":0,"k":[1,0,0,1],"ix":4},"o":{"a":0,"k":100,"ix":5},"r":1,"bm":0,"nm":"Fill 1","mn":"ADBE Vector Graphic - Fill","hd":false}],"ip":0,"op":120,"st":0,"bm":0},{"ddd":0,"ind":5,"ty":4,"nm":"Mouth","parent":6,"tt":2,"sr":1,"ks":{"o":{"a":0,"k":100,"ix":11},"r":{"a":0,"k":0,"ix":10},"p":{"a":0,"k":[0,0,0],"ix":2},"a":{"a":0,"k":[0,0,0],"ix":1},"s":{"a":0,"k":[100,100,100],"ix":6}},"ao":0,"shapes":[{"ty":"gr","it":[{"ty":"rc","d":1,"s":{"a":0,"k":[285,252],"ix":2},"p":{"a":0,"k":[0,0],"ix":3},"r":{"a":0,"k":0,"ix":4},"nm":"Rectangle Path 1","mn":"ADBE Vector Shape - Rect","hd":false},{"ty":"st","c":{"a":0,"k":[0,0,0,1],"ix":3,"x":"var $bm_rt;\n$bm_rt = thisComp.layer('Main Stroke width - Color Ctrl').effect('Base Color')('Color');"},"o":{"a":0,"k":0,"ix":4},"w":{"a":0,"k":16,"ix":5,"x":"var $bm_rt;\n$bm_rt = thisComp.layer('Main Stroke width - Color Ctrl').effect('Stroke width')('Slider');"},"lc":1,"lj":1,"ml":4,"bm":0,"nm":"Stroke 1","mn":"ADBE Vector Graphic - Stroke","hd":false},{"ty":"tr","p":{"a":0,"k":[12.75,93.75],"ix":2},"a":{"a":0,"k":[0,0],"ix":1},"s":{"a":0,"k":[100,100],"ix":3},"r":{"a":0,"k":0,"ix":6},"o":{"a":0,"k":100,"ix":7},"sk":{"a":0,"k":0,"ix":4},"sa":{"a":0,"k":0,"ix":5},"nm":"Transform"}],"nm":"Rectangle 1","np":2,"cix":2,"bm":0,"ix":1,"mn":"ADBE Vector Group","hd":false},{"ty":"gr","it":[{"ind":0,"ty":"sh","ix":1,"ks":{"a":1,"k":[{"i":{"x":0.64,"y":1},"o":{"x":0.36,"y":0},"t":0,"s":[{"i":[[0,0],[19.745,0],[0,0],[0,19.745]],"o":[[0,19.745],[0,0],[-19.745,0],[0,0]],"v":[[35.321,105.87],[-0.325,138.85],[-0.326,138.85],[-36.078,106.223]],"c":false}]},{"i":{"x":0.64,"y":1},"o":{"x":0.36,"y":0},"t":16.604,"s":[{"i":[[0,0],[19.745,0],[0,0],[0,19.745]],"o":[[0,19.745],[0,0],[-19.745,0],[0,0]],"v":[[35.321,105.87],[-0.325,138.85],[-0.326,138.85],[-36.078,106.223]],"c":false}]},{"i":{"x":0.64,"y":1},"o":{"x":0.36,"y":0},"t":35,"s":[{"i":[[0,0],[19.745,0],[0,0],[0,19.745]],"o":[[0,19.745],[0,0],[-19.745,0],[0,0]],"v":[[35.321,105.87],[-0.325,138.85],[-0.326,138.85],[-36.078,106.223]],"c":false}]},{"t":55.603515625,"s":[{"i":[[0,0],[19.745,0],[0,0],[0,19.745]],"o":[[0,19.745],[0,0],[-19.745,0],[0,0]],"v":[[35.321,105.87],[-0.325,138.85],[-0.326,138.85],[-36.078,106.223]],"c":false}]}],"ix":2},"nm":"Path 1","mn":"ADBE Vector Shape - Group","hd":false},{"ty":"st","c":{"a":0,"k":[0,0,0,1],"ix":3,"x":"var $bm_rt;\n$bm_rt = thisComp.layer('Main Stroke width - Color Ctrl').effect('Base Color')('Color');"},"o":{"a":0,"k":100,"ix":4},"w":{"a":0,"k":16,"ix":5,"x":"var $bm_rt;\n$bm_rt = thisComp.layer('Main Stroke width - Color Ctrl').effect('Stroke width')('Slider');"},"lc":2,"lj":2,"bm":0,"nm":"Stroke 1","mn":"ADBE Vector Graphic - Stroke","hd":false},{"ty":"tr","p":{"a":0,"k":[0,0],"ix":2},"a":{"a":0,"k":[0,0],"ix":1},"s":{"a":0,"k":[100,100],"ix":3},"r":{"a":0,"k":0,"ix":6},"o":{"a":0,"k":100,"ix":7},"sk":{"a":0,"k":0,"ix":4},"sa":{"a":0,"k":0,"ix":5},"nm":"Transform"}],"nm":"Group 3","np":2,"cix":2,"bm":0,"ix":2,"mn":"ADBE Vector Group","hd":false}],"ip":0,"op":120,"st":0,"bm":0},{"ddd":0,"ind":6,"ty":4,"nm":"Dalmatian","parent":1,"sr":1,"ks":{"o":{"a":0,"k":100,"ix":11},"r":{"a":1,"k":[{"i":{"x":[0.793],"y":[1]},"o":{"x":[0.207],"y":[0]},"t":0,"s":[0]},{"i":{"x":[0.793],"y":[1]},"o":{"x":[0.207],"y":[0]},"t":20.217,"s":[-18.105]},{"i":{"x":[0.793],"y":[1]},"o":{"x":[0.207],"y":[0]},"t":44.107,"s":[15.856]},{"i":{"x":[0.793],"y":[1]},"o":{"x":[0.207],"y":[0]},"t":64.324,"s":[-8]},{"i":{"x":[0.793],"y":[1]},"o":{"x":[0.207],"y":[0]},"t":85.459,"s":[4]},{"t":102,"s":[0]}],"ix":10},"p":{"a":1,"k":[{"i":{"x":0.7,"y":1},"o":{"x":0.3,"y":0},"t":0,"s":[57.75,58.25,0],"to":[0,7,0],"ti":[0,4.667,0]},{"i":{"x":0.7,"y":1},"o":{"x":0.3,"y":0},"t":18,"s":[57.75,100.25,0],"to":[0,-4.667,0],"ti":[0,0,0]},{"i":{"x":0.7,"y":1},"o":{"x":0.3,"y":0},"t":36,"s":[57.75,30.25,0],"to":[0,0,0],"ti":[0,-2,0]},{"i":{"x":0.7,"y":1},"o":{"x":0.3,"y":0},"t":53,"s":[57.75,100.25,0],"to":[0,2,0],"ti":[0,9.667,0]},{"i":{"x":0.7,"y":1},"o":{"x":0.3,"y":0},"t":71,"s":[57.75,42.25,0],"to":[0,-9.667,0],"ti":[0,-1.333,0]},{"i":{"x":0.7,"y":1},"o":{"x":0.3,"y":0},"t":90,"s":[57.75,70.25,0],"to":[0,1.333,0],"ti":[0,2,0]},{"t":105,"s":[57.75,58.25,0]}],"ix":2},"a":{"a":0,"k":[0,0,0],"ix":1},"s":{"a":0,"k":[100,100,100],"ix":6}},"ao":0,"shapes":[{"ty":"gr","it":[{"ind":0,"ty":"sh","ix":1,"ks":{"a":1,"k":[{"i":{"x":0.64,"y":1},"o":{"x":0.36,"y":0},"t":0,"s":[{"i":[[0,0],[-33.431,4.693]],"o":[[0,0],[0,0]],"v":[[-75.772,20.071],[-25.699,31.13]],"c":false}]},{"i":{"x":0.64,"y":1},"o":{"x":0.36,"y":0},"t":16.604,"s":[{"i":[[0,0],[-33.431,4.693]],"o":[[0,0],[0,0]],"v":[[-75.772,20.071],[-25.699,31.13]],"c":false}]},{"i":{"x":0.64,"y":1},"o":{"x":0.36,"y":0},"t":35,"s":[{"i":[[0,0],[-33.431,4.693]],"o":[[0,0],[0,0]],"v":[[-75.772,20.071],[-25.699,31.13]],"c":false}]},{"t":55.603515625,"s":[{"i":[[0,0],[-33.431,4.693]],"o":[[0,0],[0,0]],"v":[[-75.772,20.071],[-25.699,31.13]],"c":false}]}],"ix":2},"nm":"Path 1","mn":"ADBE Vector Shape - Group","hd":false},{"ty":"st","c":{"a":0,"k":[0,0,0,1],"ix":3,"x":"var $bm_rt;\n$bm_rt = thisComp.layer('Main Stroke width - Color Ctrl').effect('Base Color')('Color');"},"o":{"a":0,"k":100,"ix":4},"w":{"a":0,"k":16,"ix":5,"x":"var $bm_rt;\n$bm_rt = thisComp.layer('Main Stroke width - Color Ctrl').effect('Stroke width')('Slider');"},"lc":2,"lj":2,"bm":0,"nm":"Stroke 1","mn":"ADBE Vector Graphic - Stroke","hd":false},{"ty":"tr","p":{"a":0,"k":[0,0],"ix":2},"a":{"a":0,"k":[0,0],"ix":1},"s":{"a":0,"k":[100,100],"ix":3},"r":{"a":0,"k":0,"ix":6},"o":{"a":0,"k":100,"ix":7},"sk":{"a":0,"k":0,"ix":4},"sa":{"a":0,"k":0,"ix":5},"nm":"Transform"}],"nm":"Group 1","np":2,"cix":2,"bm":0,"ix":1,"mn":"ADBE Vector Group","hd":false},{"ty":"gr","it":[{"ind":0,"ty":"sh","ix":1,"ks":{"a":1,"k":[{"i":{"x":0.64,"y":1},"o":{"x":0.36,"y":0},"t":0,"s":[{"i":[[0,0],[0,0],[0,-21.365],[0,0],[13.918,0],[0,0],[10.838,34.279],[-9.811,7.636],[0,0],[0,0],[-23.138,0],[-14.508,-12.565],[0,0],[0,0],[3.748,-11.854],[28.753,0],[0,0],[0,13.918],[0,0],[11.17,18.212],[0,0]],"o":[[0,0],[-11.17,18.212],[0,0],[0,13.918],[0,0],[-28.753,0],[-3.748,-11.854],[0,0],[0,0],[14.548,-12.96],[22.731,0],[0,0],[0,0],[9.811,7.636],[-10.838,34.279],[0,0],[-13.918,0],[0,0],[0,-21.365],[0,0],[0,0]],"v":[[-61.139,-89.442],[-64.284,-84.314],[-81.365,-23.789],[-81.365,30.472],[-106.566,55.673],[-106.566,55.673],[-170.847,-44.952],[-160.744,-77.374],[-97.773,-126.384],[-58.521,-114.773],[-0.002,-135.85],[57.744,-115.452],[96.313,-126.384],[159.285,-77.374],[169.388,-44.952],[105.106,55.673],[105.106,55.673],[79.906,30.472],[79.906,-23.789],[62.824,-84.314],[59.679,-89.442]],"c":false}]},{"i":{"x":0.64,"y":1},"o":{"x":0.36,"y":0},"t":17,"s":[{"i":[[0,0],[0,0],[0,-21.365],[0.019,-0.02],[13.741,-2.191],[0,0],[16.098,32.137],[-8.484,9.084],[-0.023,-0.012],[0,0],[-23.138,0],[-14.508,-12.565],[-0.024,0.002],[0,0],[5.852,-10.966],[28.262,5.259],[0,0],[2.199,6.548],[0,0],[11.17,18.212],[0,0]],"o":[[0,0],[-11.17,18.212],[0,0],[-0.019,13.921],[0,0],[-28.388,4.527],[-5.567,-11.114],[0,0],[0.023,0.012],[14.548,-12.96],[22.731,0],[0,0],[0.024,-0.002],[8.247,9.3],[-16.923,31.711],[0,0],[-13.68,-2.546],[-0.015,-0.01],[0,-21.365],[0,0],[0,0]],"v":[[-61.139,-89.442],[-64.284,-84.314],[-81.371,-23.789],[-81.791,-0.399],[-81.122,61.315],[-81.122,61.315],[-160.431,-27.909],[-155.561,-61.51],[-101.106,-119.812],[-58.521,-114.773],[-0.002,-135.85],[57.744,-115.452],[99.503,-118.279],[152.434,-58.588],[156.434,-24.872],[74.846,62.275],[74.846,62.275],[80.188,6.546],[79.906,-23.789],[62.824,-84.314],[59.679,-89.442]],"c":false}]},{"i":{"x":0.64,"y":1},"o":{"x":0.36,"y":0},"t":35,"s":[{"i":[[0,0],[0,0],[0,-21.365],[15.838,-16.766],[12.382,6.355],[0,0],[-6.009,35.446],[-12.216,2.314],[-19.141,-10.31],[0,0],[-23.138,0],[-14.508,-12.565],[-20.23,2.08],[0,0],[-1.398,-12.354],[26.267,-11.696],[0,0],[12.586,8.047],[0,0],[11.17,18.212],[0,0]],"o":[[0,0],[-11.17,18.212],[0,0],[-15.838,16.766],[0,0],[-25.581,-13.128],[2.078,-12.258],[0,0],[19.141,10.31],[14.548,-12.96],[22.731,0],[0,0],[20.23,-2.08],[12.069,2.985],[4.043,35.724],[0,0],[-12.714,5.661],[-12.586,-8.047],[0,-21.365],[0,0],[0,0]],"v":[[-61.139,-89.442],[-64.284,-84.314],[-85.865,-23.789],[-139.162,4.734],[-173.088,15.648],[-173.088,15.648],[-184.335,-103.225],[-160.543,-127.458],[-82.141,-142.31],[-58.521,-114.773],[-0.002,-135.85],[57.744,-115.452],[84.77,-141.92],[162.232,-122.763],[184.65,-97.254],[166.858,20.817],[166.858,20.817],[133.586,8.047],[79.906,-23.789],[62.824,-84.314],[59.679,-89.442]],"c":false}]},{"t":55.603515625,"s":[{"i":[[0,0],[0,0],[0,-21.365],[0,0],[13.918,0],[0,0],[10.838,34.279],[-9.811,7.636],[0,0],[0,0],[-23.138,0],[-14.508,-12.565],[0,0],[0,0],[3.748,-11.854],[28.753,0],[0,0],[0,13.918],[0,0],[11.17,18.212],[0,0]],"o":[[0,0],[-11.17,18.212],[0,0],[0,13.918],[0,0],[-28.753,0],[-3.748,-11.854],[0,0],[0,0],[14.548,-12.96],[22.731,0],[0,0],[0,0],[9.811,7.636],[-10.838,34.279],[0,0],[-13.918,0],[0,0],[0,-21.365],[0,0],[0,0]],"v":[[-61.139,-89.442],[-64.284,-84.314],[-81.365,-23.789],[-81.365,30.472],[-106.566,55.673],[-106.566,55.673],[-170.847,-44.952],[-160.744,-77.374],[-97.773,-126.384],[-58.521,-114.773],[-0.002,-135.85],[57.744,-115.452],[96.313,-126.384],[159.285,-77.374],[169.388,-44.952],[105.106,55.673],[105.106,55.673],[79.906,30.472],[79.906,-23.789],[62.824,-84.314],[59.679,-89.442]],"c":false}]}],"ix":2},"nm":"Path 1","mn":"ADBE Vector Shape - Group","hd":false},{"ty":"st","c":{"a":0,"k":[0,0,0,1],"ix":3,"x":"var $bm_rt;\n$bm_rt = thisComp.layer('Main Stroke width - Color Ctrl').effect('Base Color')('Color');"},"o":{"a":0,"k":100,"ix":4},"w":{"a":0,"k":16,"ix":5,"x":"var $bm_rt;\n$bm_rt = thisComp.layer('Main Stroke width - Color Ctrl').effect('Stroke width')('Slider');"},"lc":2,"lj":2,"bm":0,"nm":"Stroke 1","mn":"ADBE Vector Graphic - Stroke","hd":false},{"ty":"tr","p":{"a":0,"k":[0,0],"ix":2},"a":{"a":0,"k":[0,0],"ix":1},"s":{"a":0,"k":[100,100],"ix":3},"r":{"a":0,"k":0,"ix":6},"o":{"a":0,"k":100,"ix":7},"sk":{"a":0,"k":0,"ix":4},"sa":{"a":0,"k":0,"ix":5},"nm":"Transform"}],"nm":"Group 2","np":2,"cix":2,"bm":0,"ix":2,"mn":"ADBE Vector Group","hd":false},{"ty":"gr","it":[{"ind":0,"ty":"sh","ix":1,"ks":{"a":1,"k":[{"i":{"x":0.64,"y":1},"o":{"x":0.36,"y":0},"t":0,"s":[{"i":[[0,0],[0,0],[16.717,0],[0,0],[3.257,13.204],[3.628,12.506],[0,0]],"o":[[0,0],[0,16.717],[0,0],[-14.21,0],[-3.119,-12.643],[0,0],[0,0]],"v":[[-0.73,65.615],[-0.73,73.508],[-29.998,103.778],[-29.998,103.778],[-59.388,80.783],[-69.131,42.961],[-81.365,0.792]],"c":false}]},{"i":{"x":0.833,"y":0.833},"o":{"x":0.36,"y":0},"t":16.604,"s":[{"i":[[0,0],[0,0],[16.717,0],[0,0],[3.257,13.204],[3.628,12.506],[0,0]],"o":[[0,0],[0,16.717],[0,0],[-14.21,0],[-3.119,-12.643],[0,0],[0,0]],"v":[[-0.73,65.615],[-0.73,73.508],[-29.998,103.778],[-29.998,103.778],[-59.388,80.783],[-69.131,42.961],[-81.365,0.792]],"c":false}]},{"i":{"x":0.64,"y":1},"o":{"x":0.167,"y":0.167},"t":27,"s":[{"i":[[0,0],[0,0],[16.717,0],[0,0],[3.257,13.204],[3.628,12.506],[0,0]],"o":[[0,0],[0,16.717],[0,0],[-14.21,0],[-3.119,-12.643],[0,0],[0,0]],"v":[[-0.73,65.615],[-0.73,73.508],[-29.998,103.778],[-29.998,103.778],[-59.388,80.783],[-69.131,42.961],[-83.82,-23.415]],"c":false}]},{"i":{"x":0.833,"y":0.833},"o":{"x":0.36,"y":0},"t":35,"s":[{"i":[[0,0],[0,0],[16.717,0],[0,0],[3.257,13.204],[3.628,12.506],[0,0]],"o":[[0,0],[0,16.717],[0,0],[-14.21,0],[-3.119,-12.643],[0,0],[0,0]],"v":[[-0.73,65.615],[-0.73,73.508],[-29.998,103.778],[-29.998,103.778],[-59.388,80.783],[-69.131,42.961],[-86.365,-20.208]],"c":false}]},{"i":{"x":0.64,"y":1},"o":{"x":0.167,"y":0.167},"t":46,"s":[{"i":[[0,0],[0,0],[16.717,0],[0,0],[3.257,13.204],[3.628,12.506],[0,0]],"o":[[0,0],[0,16.717],[0,0],[-14.21,0],[-3.119,-12.643],[0,0],[0,0]],"v":[[-0.73,65.615],[-0.73,73.508],[-29.998,103.778],[-29.998,103.778],[-59.388,80.783],[-69.131,42.961],[-85.749,-14.753]],"c":false}]},{"t":55.603515625,"s":[{"i":[[0,0],[0,0],[16.717,0],[0,0],[3.257,13.204],[3.628,12.506],[0,0]],"o":[[0,0],[0,16.717],[0,0],[-14.21,0],[-3.119,-12.643],[0,0],[0,0]],"v":[[-0.73,65.615],[-0.73,73.508],[-29.998,103.778],[-29.998,103.778],[-59.388,80.783],[-69.131,42.961],[-81.365,0.792]],"c":false}]}],"ix":2},"nm":"Path 1","mn":"ADBE Vector Shape - Group","hd":false},{"ty":"st","c":{"a":0,"k":[0,0,0,1],"ix":3,"x":"var $bm_rt;\n$bm_rt = thisComp.layer('Main Stroke width - Color Ctrl').effect('Base Color')('Color');"},"o":{"a":0,"k":100,"ix":4},"w":{"a":0,"k":16,"ix":5,"x":"var $bm_rt;\n$bm_rt = thisComp.layer('Main Stroke width - Color Ctrl').effect('Stroke width')('Slider');"},"lc":2,"lj":2,"bm":0,"nm":"Stroke 1","mn":"ADBE Vector Graphic - Stroke","hd":false},{"ty":"tr","p":{"a":0,"k":[0,0],"ix":2},"a":{"a":0,"k":[0,0],"ix":1},"s":{"a":0,"k":[100,100],"ix":3},"r":{"a":0,"k":0,"ix":6},"o":{"a":0,"k":100,"ix":7},"sk":{"a":0,"k":0,"ix":4},"sa":{"a":0,"k":0,"ix":5},"nm":"Transform"}],"nm":"Group 4","np":2,"cix":2,"bm":0,"ix":3,"mn":"ADBE Vector Group","hd":false},{"ty":"gr","it":[{"ind":0,"ty":"sh","ix":1,"ks":{"a":1,"k":[{"i":{"x":0.64,"y":1},"o":{"x":0.36,"y":0},"t":0,"s":[{"i":[[0,0],[0,0],[2.971,-14.517],[14.628,0],[0,0],[0,16.717],[0,0]],"o":[[0,0],[-3.921,14.289],[-2.823,13.793],[0,0],[-16.718,0],[0,0],[0,0]],"v":[[79.906,5.896],[71.512,36.488],[60.739,79.609],[31.084,103.778],[31.084,103.778],[-0.73,73.508],[-0.73,66.452]],"c":false}]},{"i":{"x":0.833,"y":0.833},"o":{"x":0.36,"y":0},"t":16.604,"s":[{"i":[[0,0],[0,0],[2.971,-14.517],[14.628,0],[0,0],[0,16.717],[0,0]],"o":[[0,0],[-3.921,14.289],[-2.823,13.793],[0,0],[-16.718,0],[0,0],[0,0]],"v":[[79.906,5.896],[71.512,36.488],[60.739,79.609],[31.084,103.778],[31.084,103.778],[-0.73,73.508],[-0.73,66.452]],"c":false}]},{"i":{"x":0.64,"y":1},"o":{"x":0.167,"y":0.167},"t":27,"s":[{"i":[[0,0],[0,0],[2.971,-14.517],[14.628,0],[0,0],[0,16.717],[0,0]],"o":[[0,0],[-3.921,14.289],[-2.823,13.793],[0,0],[-16.718,0],[0,0],[0,0]],"v":[[79.12,-20.726],[71.512,36.488],[60.739,79.609],[31.084,103.778],[31.084,103.778],[-0.73,73.508],[-0.73,66.452]],"c":false}]},{"i":{"x":0.833,"y":0.833},"o":{"x":0.36,"y":0},"t":35,"s":[{"i":[[0,0],[0,0],[2.971,-14.517],[14.628,0],[0,0],[0,16.717],[0,0]],"o":[[0,0],[-3.921,14.289],[-2.823,13.793],[0,0],[-16.718,0],[0,0],[0,0]],"v":[[79.906,-22.104],[71.512,36.488],[60.739,79.609],[31.084,103.778],[31.084,103.778],[-0.73,73.508],[-0.73,66.452]],"c":false}]},{"i":{"x":0.64,"y":1},"o":{"x":0.167,"y":0.167},"t":46,"s":[{"i":[[0,0],[0,0],[2.971,-14.517],[14.628,0],[0,0],[0,16.717],[0,0]],"o":[[0,0],[-3.921,14.289],[-2.823,13.793],[0,0],[-16.718,0],[0,0],[0,0]],"v":[[80.018,-15.964],[71.512,36.488],[60.739,79.609],[31.084,103.778],[31.084,103.778],[-0.73,73.508],[-0.73,66.452]],"c":false}]},{"t":55.603515625,"s":[{"i":[[0,0],[0,0],[2.971,-14.517],[14.628,0],[0,0],[0,16.717],[0,0]],"o":[[0,0],[-3.921,14.289],[-2.823,13.793],[0,0],[-16.718,0],[0,0],[0,0]],"v":[[79.906,5.896],[71.512,36.488],[60.739,79.609],[31.084,103.778],[31.084,103.778],[-0.73,73.508],[-0.73,66.452]],"c":false}]}],"ix":2},"nm":"Path 1","mn":"ADBE Vector Shape - Group","hd":false},{"ty":"st","c":{"a":0,"k":[0,0,0,1],"ix":3,"x":"var $bm_rt;\n$bm_rt = thisComp.layer('Main Stroke width - Color Ctrl').effect('Base Color')('Color');"},"o":{"a":0,"k":100,"ix":4},"w":{"a":0,"k":16,"ix":5,"x":"var $bm_rt;\n$bm_rt = thisComp.layer('Main Stroke width - Color Ctrl').effect('Stroke width')('Slider');"},"lc":2,"lj":2,"bm":0,"nm":"Stroke 1","mn":"ADBE Vector Graphic - Stroke","hd":false},{"ty":"tr","p":{"a":0,"k":[0,0],"ix":2},"a":{"a":0,"k":[0,0],"ix":1},"s":{"a":0,"k":[100,100],"ix":3},"r":{"a":0,"k":0,"ix":6},"o":{"a":0,"k":100,"ix":7},"sk":{"a":0,"k":0,"ix":4},"sa":{"a":0,"k":0,"ix":5},"nm":"Transform"}],"nm":"Group 5","np":2,"cix":2,"bm":0,"ix":4,"mn":"ADBE Vector Group","hd":false},{"ty":"gr","it":[{"ind":0,"ty":"sh","ix":1,"ks":{"a":1,"k":[{"i":{"x":0.64,"y":1},"o":{"x":0.36,"y":0},"t":0,"s":[{"i":[[0,0],[0,0],[-5.74,6.314],[-6.68,0],[0,0],[-4.165,-4.582],[6.657,-5.338]],"o":[[0,0],[-6.657,-5.338],[4.165,-4.582],[0,0],[6.68,0],[5.74,6.314],[0,0]],"v":[[-0.73,65.615],[-21.336,49.09],[-23.208,27.53],[-6.354,20.071],[4.895,20.071],[21.749,27.53],[19.877,49.09]],"c":true}]},{"i":{"x":0.64,"y":1},"o":{"x":0.36,"y":0},"t":16.604,"s":[{"i":[[0,0],[0,0],[-5.74,6.314],[-6.68,0],[0,0],[-4.165,-4.582],[6.657,-5.338]],"o":[[0,0],[-6.657,-5.338],[4.165,-4.582],[0,0],[6.68,0],[5.74,6.314],[0,0]],"v":[[-0.73,65.615],[-21.336,49.09],[-23.208,27.53],[-6.354,20.071],[4.895,20.071],[21.749,27.53],[19.877,49.09]],"c":true}]},{"i":{"x":0.64,"y":1},"o":{"x":0.36,"y":0},"t":35,"s":[{"i":[[0,0],[0,0],[-5.74,6.314],[-6.68,0],[0,0],[-4.165,-4.582],[6.657,-5.338]],"o":[[0,0],[-6.657,-5.338],[4.165,-4.582],[0,0],[6.68,0],[5.74,6.314],[0,0]],"v":[[-0.73,65.615],[-21.336,49.09],[-23.208,27.53],[-6.354,20.071],[4.895,20.071],[21.749,27.53],[19.877,49.09]],"c":true}]},{"t":55.603515625,"s":[{"i":[[0,0],[0,0],[-5.74,6.314],[-6.68,0],[0,0],[-4.165,-4.582],[6.657,-5.338]],"o":[[0,0],[-6.657,-5.338],[4.165,-4.582],[0,0],[6.68,0],[5.74,6.314],[0,0]],"v":[[-0.73,65.615],[-21.336,49.09],[-23.208,27.53],[-6.354,20.071],[4.895,20.071],[21.749,27.53],[19.877,49.09]],"c":true}]}],"ix":2},"nm":"Path 1","mn":"ADBE Vector Shape - Group","hd":false},{"ty":"st","c":{"a":0,"k":[0,0,0,1],"ix":3,"x":"var $bm_rt;\n$bm_rt = thisComp.layer('Main Stroke width - Color Ctrl').effect('Base Color')('Color');"},"o":{"a":0,"k":100,"ix":4},"w":{"a":0,"k":16,"ix":5,"x":"var $bm_rt;\n$bm_rt = thisComp.layer('Main Stroke width - Color Ctrl').effect('Stroke width')('Slider');"},"lc":2,"lj":2,"bm":0,"nm":"Stroke 1","mn":"ADBE Vector Graphic - Stroke","hd":false},{"ty":"tr","p":{"a":0,"k":[0,0],"ix":2},"a":{"a":0,"k":[0,0],"ix":1},"s":{"a":0,"k":[100,100],"ix":3},"r":{"a":0,"k":0,"ix":6},"o":{"a":0,"k":100,"ix":7},"sk":{"a":0,"k":0,"ix":4},"sa":{"a":0,"k":0,"ix":5},"nm":"Transform"}],"nm":"Group 6","np":2,"cix":2,"bm":0,"ix":5,"mn":"ADBE Vector Group","hd":false},{"ty":"gr","it":[{"ty":"gr","it":[{"ind":0,"ty":"sh","ix":1,"ks":{"a":1,"k":[{"i":{"x":0.64,"y":1},"o":{"x":0.36,"y":0},"t":0,"s":[{"i":[[0,0],[0,0]],"o":[[0,0],[0,0]],"v":[[38.268,-31.947],[38.268,-10.548]],"c":false}]},{"i":{"x":0.64,"y":1},"o":{"x":0.36,"y":0},"t":16.604,"s":[{"i":[[0,0],[0,0]],"o":[[0,0],[0,0]],"v":[[38.268,-31.947],[38.268,-10.548]],"c":false}]},{"i":{"x":0.64,"y":1},"o":{"x":0.36,"y":0},"t":35,"s":[{"i":[[0,0],[0,0]],"o":[[0,0],[0,0]],"v":[[38.268,-31.947],[38.268,-10.548]],"c":false}]},{"t":55.603515625,"s":[{"i":[[0,0],[0,0]],"o":[[0,0],[0,0]],"v":[[38.268,-31.947],[38.268,-10.548]],"c":false}]}],"ix":2},"nm":"Path 1","mn":"ADBE Vector Shape - Group","hd":false},{"ty":"st","c":{"a":0,"k":[1,0.698039215686,0.298039215686,1],"ix":3,"x":"var $bm_rt;\n$bm_rt = thisComp.layer('Main Stroke width - Color Ctrl').effect('Base Color')('Color');"},"o":{"a":0,"k":100,"ix":4},"w":{"a":0,"k":16,"ix":5,"x":"var $bm_rt;\n$bm_rt = thisComp.layer('Main Stroke width - Color Ctrl').effect('Stroke width')('Slider');"},"lc":2,"lj":2,"bm":0,"nm":"Stroke 1","mn":"ADBE Vector Graphic - Stroke","hd":false},{"ty":"tr","p":{"a":0,"k":[0,0],"ix":2},"a":{"a":0,"k":[0,0],"ix":1},"s":{"a":0,"k":[100,100],"ix":3},"r":{"a":0,"k":0,"ix":6},"o":{"a":0,"k":100,"ix":7},"sk":{"a":0,"k":0,"ix":4},"sa":{"a":0,"k":0,"ix":5},"nm":"Transform"}],"nm":"Group 1","np":2,"cix":2,"bm":0,"ix":1,"mn":"ADBE Vector Group","hd":false},{"ty":"gr","it":[{"ind":0,"ty":"sh","ix":1,"ks":{"a":1,"k":[{"i":{"x":0.64,"y":1},"o":{"x":0.36,"y":0},"t":0,"s":[{"i":[[0,0],[0,0]],"o":[[0,0],[0,0]],"v":[[-38.273,-31.947],[-38.273,-10.548]],"c":false}]},{"i":{"x":0.64,"y":1},"o":{"x":0.36,"y":0},"t":16.604,"s":[{"i":[[0,0],[0,0]],"o":[[0,0],[0,0]],"v":[[-38.273,-31.947],[-38.273,-10.548]],"c":false}]},{"i":{"x":0.64,"y":1},"o":{"x":0.36,"y":0},"t":35,"s":[{"i":[[0,0],[0,0]],"o":[[0,0],[0,0]],"v":[[-38.273,-31.947],[-38.273,-10.548]],"c":false}]},{"t":55.603515625,"s":[{"i":[[0,0],[0,0]],"o":[[0,0],[0,0]],"v":[[-38.273,-31.947],[-38.273,-10.548]],"c":false}]}],"ix":2},"nm":"Path 1","mn":"ADBE Vector Shape - Group","hd":false},{"ty":"st","c":{"a":0,"k":[1,0.698039215686,0.298039215686,1],"ix":3,"x":"var $bm_rt;\n$bm_rt = thisComp.layer('Main Stroke width - Color Ctrl').effect('Base Color')('Color');"},"o":{"a":0,"k":100,"ix":4},"w":{"a":0,"k":16,"ix":5,"x":"var $bm_rt;\n$bm_rt = thisComp.layer('Main Stroke width - Color Ctrl').effect('Stroke width')('Slider');"},"lc":2,"lj":2,"bm":0,"nm":"Stroke 1","mn":"ADBE Vector Graphic - Stroke","hd":false},{"ty":"tr","p":{"a":0,"k":[0,0],"ix":2},"a":{"a":0,"k":[0,0],"ix":1},"s":{"a":0,"k":[100,100],"ix":3},"r":{"a":0,"k":0,"ix":6},"o":{"a":0,"k":100,"ix":7},"sk":{"a":0,"k":0,"ix":4},"sa":{"a":0,"k":0,"ix":5},"nm":"Transform"}],"nm":"Group 2","np":2,"cix":2,"bm":0,"ix":2,"mn":"ADBE Vector Group","hd":false},{"ty":"fl","c":{"a":0,"k":[1,0.698039215686,0.298039215686,1],"ix":4},"o":{"a":0,"k":100,"ix":5},"r":1,"bm":0,"nm":"Fill 1","mn":"ADBE Vector Graphic - Fill","hd":false},{"ty":"tr","p":{"a":0,"k":[0,0],"ix":2},"a":{"a":0,"k":[0,0],"ix":1},"s":{"a":0,"k":[100,100],"ix":3},"r":{"a":0,"k":0,"ix":6},"o":{"a":0,"k":100,"ix":7},"sk":{"a":0,"k":0,"ix":4},"sa":{"a":0,"k":0,"ix":5},"nm":"Transform"}],"nm":"Group 7","np":3,"cix":2,"bm":0,"ix":6,"mn":"ADBE Vector Group","hd":false},{"ty":"gr","it":[{"ind":0,"ty":"sh","ix":1,"ks":{"a":1,"k":[{"i":{"x":0.64,"y":1},"o":{"x":0.36,"y":0},"t":0,"s":[{"i":[[0,0],[0.493,-21.387],[7.632,-6.693]],"o":[[22.158,-5.185],[-0.234,10.152],[0,0]],"v":[[-159.449,-31.909],[-118.625,4.377],[-131.478,32.004]],"c":false}]},{"i":{"x":0.64,"y":1},"o":{"x":0.36,"y":0},"t":16.604,"s":[{"i":[[0,0],[-2.896,-21.195],[6.477,-7.816]],"o":[[21.059,-8.624],[1.375,10.061],[0,0]],"v":[[-147.085,-16.743],[-101.035,12.627],[-109.356,41.94]],"c":false}]},{"i":{"x":0.64,"y":1},"o":{"x":0.36,"y":0},"t":35,"s":[{"i":[[0,0],[10.204,-18.802],[9.846,-2.47]],"o":[[22.081,5.504],[-4.843,8.925],[0,0]],"v":[[-180.15,-86.417],[-160.396,-35.495],[-184.445,-16.785]],"c":false}]},{"t":55.603515625,"s":[{"i":[[0,0],[0.493,-21.387],[7.632,-6.693]],"o":[[22.158,-5.185],[-0.234,10.152],[0,0]],"v":[[-159.449,-31.909],[-118.625,4.377],[-131.478,32.004]],"c":false}]}],"ix":2},"nm":"Path 1","mn":"ADBE Vector Shape - Group","hd":false},{"ty":"st","c":{"a":0,"k":[0.20000000298,0.800000011921,0.800000011921,1],"ix":3,"x":"var $bm_rt;\n$bm_rt = thisComp.layer('Main Stroke width - Color Ctrl').effect('Highlight')('Color');"},"o":{"a":0,"k":100,"ix":4},"w":{"a":0,"k":16,"ix":5,"x":"var $bm_rt;\n$bm_rt = thisComp.layer('Main Stroke width - Color Ctrl').effect('Stroke width')('Slider');"},"lc":2,"lj":2,"bm":0,"nm":"Stroke 1","mn":"ADBE Vector Graphic - Stroke","hd":false},{"ty":"tr","p":{"a":0,"k":[0,0],"ix":2},"a":{"a":0,"k":[0,0],"ix":1},"s":{"a":0,"k":[100,100],"ix":3},"r":{"a":0,"k":0,"ix":6},"o":{"a":0,"k":100,"ix":7},"sk":{"a":0,"k":0,"ix":4},"sa":{"a":0,"k":0,"ix":5},"nm":"Transform"}],"nm":"Group 8","np":2,"cix":2,"bm":0,"ix":7,"mn":"ADBE Vector Group","hd":false},{"ty":"gr","it":[{"ind":0,"ty":"sh","ix":1,"ks":{"a":1,"k":[{"i":{"x":0.64,"y":1},"o":{"x":0.36,"y":0},"t":0,"s":[{"i":[[0,0],[-0.157,-10.538],[0,0],[-21.919,3.823]],"o":[[-7.661,7.238],[0,0],[0.355,23.805],[0,0]],"v":[[131.603,-92.199],[118.947,-62.218],[118.947,-62.218],[162.891,-25.68]],"c":false}]},{"i":{"x":0.64,"y":1},"o":{"x":0.36,"y":0},"t":16.604,"s":[{"i":[[0,0],[1.78,-10.388],[0,0],[-22.248,-0.266]],"o":[[-8.86,5.708],[0,0],[-4.022,23.466],[0,0]],"v":[[127.933,-78.168],[109.987,-51.02],[109.987,-51.02],[146.476,-7.035]],"c":false}]},{"i":{"x":0.64,"y":1},"o":{"x":0.36,"y":0},"t":35,"s":[{"i":[[0,0],[-4.43,-9.563],[0,0],[-18.468,12.409]],"o":[[-4.055,9.728],[0,0],[10.008,21.602],[0,0]],"v":[[130.913,-125.046],[131.547,-92.509],[131.547,-92.509],[186.554,-77.007]],"c":false}]},{"t":55.603515625,"s":[{"i":[[0,0],[-0.157,-10.538],[0,0],[-21.919,3.823]],"o":[[-7.661,7.238],[0,0],[0.355,23.805],[0,0]],"v":[[131.603,-92.199],[118.947,-62.218],[118.947,-62.218],[162.891,-25.68]],"c":false}]}],"ix":2},"nm":"Path 1","mn":"ADBE Vector Shape - Group","hd":false},{"ty":"st","c":{"a":0,"k":[0.20000000298,0.800000011921,0.800000011921,1],"ix":3,"x":"var $bm_rt;\n$bm_rt = thisComp.layer('Main Stroke width - Color Ctrl').effect('Highlight')('Color');"},"o":{"a":0,"k":100,"ix":4},"w":{"a":0,"k":16,"ix":5,"x":"var $bm_rt;\n$bm_rt = thisComp.layer('Main Stroke width - Color Ctrl').effect('Stroke width')('Slider');"},"lc":2,"lj":2,"bm":0,"nm":"Stroke 1","mn":"ADBE Vector Graphic - Stroke","hd":false},{"ty":"tr","p":{"a":0,"k":[0,0],"ix":2},"a":{"a":0,"k":[0,0],"ix":1},"s":{"a":0,"k":[100,100],"ix":3},"r":{"a":0,"k":0,"ix":6},"o":{"a":0,"k":100,"ix":7},"sk":{"a":0,"k":0,"ix":4},"sa":{"a":0,"k":0,"ix":5},"nm":"Transform"}],"nm":"Group 9","np":2,"cix":2,"bm":0,"ix":8,"mn":"ADBE Vector Group","hd":false},{"ty":"gr","it":[{"ind":0,"ty":"sh","ix":1,"ks":{"a":1,"k":[{"i":{"x":0.64,"y":1},"o":{"x":0.36,"y":0},"t":0,"s":[{"i":[[0,0],[-28.023,-9.423],[0,0],[0,0]],"o":[[0,0],[19.343,6.505],[0,0],[0,0]],"v":[[-78.606,-48.899],[-26.566,-62.09],[0.272,-31.947],[-0.359,20.071]],"c":false}]},{"i":{"x":0.64,"y":1},"o":{"x":0.36,"y":0},"t":16.604,"s":[{"i":[[0,0],[-28.023,-9.423],[0,0],[0,0]],"o":[[0,0],[19.343,6.505],[0,0],[0,0]],"v":[[-78.606,-48.899],[-26.566,-62.09],[0.272,-31.947],[-0.359,20.071]],"c":false}]},{"i":{"x":0.64,"y":1},"o":{"x":0.36,"y":0},"t":35,"s":[{"i":[[0,0],[-28.023,-9.423],[0,0],[0,0]],"o":[[0,0],[19.343,6.505],[0,0],[0,0]],"v":[[-78.606,-48.899],[-26.566,-62.09],[0.272,-31.947],[-0.359,20.071]],"c":false}]},{"t":55.603515625,"s":[{"i":[[0,0],[-28.023,-9.423],[0,0],[0,0]],"o":[[0,0],[19.343,6.505],[0,0],[0,0]],"v":[[-78.606,-48.899],[-26.566,-62.09],[0.272,-31.947],[-0.359,20.071]],"c":false}]}],"ix":2},"nm":"Path 1","mn":"ADBE Vector Shape - Group","hd":false},{"ty":"st","c":{"a":0,"k":[0.20000000298,0.800000011921,0.800000011921,1],"ix":3,"x":"var $bm_rt;\n$bm_rt = thisComp.layer('Main Stroke width - Color Ctrl').effect('Highlight')('Color');"},"o":{"a":0,"k":100,"ix":4},"w":{"a":0,"k":16,"ix":5,"x":"var $bm_rt;\n$bm_rt = thisComp.layer('Main Stroke width - Color Ctrl').effect('Stroke width')('Slider');"},"lc":2,"lj":2,"bm":0,"nm":"Stroke 1","mn":"ADBE Vector Graphic - Stroke","hd":false},{"ty":"tr","p":{"a":0,"k":[0,0],"ix":2},"a":{"a":0,"k":[0,0],"ix":1},"s":{"a":0,"k":[100,100],"ix":3},"r":{"a":0,"k":0,"ix":6},"o":{"a":0,"k":100,"ix":7},"sk":{"a":0,"k":0,"ix":4},"sa":{"a":0,"k":0,"ix":5},"nm":"Transform"}],"nm":"Group 10","np":2,"cix":2,"bm":0,"ix":9,"mn":"ADBE Vector Group","hd":false}],"ip":0,"op":120,"st":0,"bm":0}]}],"layers":[{"ddd":0,"ind":1,"ty":0,"nm":"Pre-comp 1","refId":"comp_0","sr":1,"ks":{"o":{"a":0,"k":100,"ix":11},"r":{"a":0,"k":0,"ix":10},"p":{"a":0,"k":[250,250,0],"ix":2},"a":{"a":0,"k":[250,250,0],"ix":1},"s":{"a":0,"k":[-100,100,100],"ix":6}},"ao":0,"w":500,"h":500,"ip":0,"op":120,"st":0,"bm":0}],"markers":[]}
